[
  {
    "id": "hft_001",
    "asset": "BTC",
    "side": "DOWN",
    "entry_price": 0.33,
    "entry_time": "2026-05-07T23:43:57.435137+00:00",
    "stake": 1.2,
    "shares": 3.6364,
    "signal_score": -0.378,
    "status": "sold",
    "exit_price": 0.1781,
    "exit_time": "2026-05-07T23:44:12.793415+00:00",
    "pnl": -0.55,
    "market_slug": "btc-updown-5m-1778197200",
    "gamma_id": "2178076",
    "event_start": "2026-05-07T23:40:00+00:00",
    "event_end": "2026-05-07T23:45:00+00:00",
    "token_id": "15668535656758693929742115453812924657387861333186357871497795181781102289048",
    "exit_reason": "stop_loss",
    "hindsight_reviewed": true,
    "hindsight": {
      "would_have_won": false,
      "held_pnl": -1.2,
      "actual_pnl": -0.55,
      "decision": "GOOD",
      "difference": 0.65,
      "resolution": "UP"
    }
  },
  {
    "id": "hft_002",
    "asset": "BTC",
    "side": "DOWN",
    "entry_price": 0.54,
    "entry_time": "2026-05-07T23:47:02.232654+00:00",
    "stake": 1.17,
    "shares": 2.1667,
    "signal_score": -0.4677,
    "status": "sold",
    "exit_price": 0.34,
    "exit_time": "2026-05-07T23:48:11.765165+00:00",
    "pnl": -0.43,
    "market_slug": "btc-updown-5m-1778197500",
    "gamma_id": "2178081",
    "event_start": "2026-05-07T23:45:00+00:00",
    "event_end": "2026-05-07T23:50:00+00:00",
    "token_id": "109656615444509633010791402997414019325105820317785000009343063943411992254470",
    "exit_reason": "stop_loss",
    "hindsight_reviewed": true,
    "hindsight": {
      "would_have_won": false,
      "held_pnl": -1.17,
      "actual_pnl": -0.43,
      "decision": "GOOD",
      "difference": 0.74,
      "resolution": "UP"
    }
  },
  {
    "id": "hft_003",
    "asset": "BTC",
    "side": "DOWN",
    "entry_price": 0.35,
    "entry_time": "2026-05-07T23:48:12.293464+00:00",
    "stake": 1.17,
    "shares": 3.3429,
    "signal_score": -0.4063,
    "status": "sold",
    "exit_price": 0.12,
    "exit_time": "2026-05-07T23:48:27.307062+00:00",
    "pnl": -0.77,
    "market_slug": "btc-updown-5m-1778197500",
    "gamma_id": "2178081",
    "event_start": "2026-05-07T23:45:00+00:00",
    "event_end": "2026-05-07T23:50:00+00:00",
    "token_id": "109656615444509633010791402997414019325105820317785000009343063943411992254470",
    "exit_reason": "stop_loss",
    "hindsight_reviewed": true,
    "hindsight": {
      "would_have_won": false,
      "held_pnl": -1.17,
      "actual_pnl": -0.77,
      "decision": "GOOD",
      "difference": 0.4,
      "resolution": "UP"
    }
  },
  {
    "id": "hft_004",
    "asset": "BTC",
    "side": "DOWN",
    "entry_price": 0.12,
    "entry_time": "2026-05-07T23:48:27.857766+00:00",
    "stake": 1.15,
    "shares": 9.5833,
    "signal_score": -0.4272,
    "status": "sold",
    "exit_price": 0.03,
    "exit_time": "2026-05-07T23:49:22.102482+00:00",
    "pnl": -0.86,
    "market_slug": "btc-updown-5m-1778197500",
    "gamma_id": "2178081",
    "event_start": "2026-05-07T23:45:00+00:00",
    "event_end": "2026-05-07T23:50:00+00:00",
    "token_id": "109656615444509633010791402997414019325105820317785000009343063943411992254470",
    "_high_watermark": 0.375,
    "exit_reason": "stop_loss",
    "hindsight_reviewed": true,
    "hindsight": {
      "would_have_won": false,
      "held_pnl": -1.15,
      "actual_pnl": -0.86,
      "decision": "GOOD",
      "difference": 0.29,
      "resolution": "UP"
    }
  },
  {
    "id": "hft_005",
    "asset": "ETH",
    "side": "DOWN",
    "entry_price": 0.06,
    "entry_time": "2026-05-07T23:48:46.223978+00:00",
    "stake": 1.11,
    "shares": 18.5,
    "signal_score": -0.31,
    "status": "sold",
    "exit_price": 0.04,
    "exit_time": "2026-05-07T23:49:03.013695+00:00",
    "pnl": -0.37,
    "market_slug": "eth-updown-5m-1778197500",
    "gamma_id": "2178089",
    "event_start": "2026-05-07T23:45:00+00:00",
    "event_end": "2026-05-07T23:50:00+00:00",
    "token_id": "19979972433790377529106966792111990178797270136533581849845447966706229475604",
    "_high_watermark": 0.11499999999999999,
    "exit_reason": "trailing_stop",
    "hindsight_reviewed": true,
    "hindsight": {
      "would_have_won": false,
      "held_pnl": -1.11,
      "actual_pnl": -0.37,
      "decision": "GOOD",
      "difference": 0.74,
      "resolution": "UP"
    }
  },
  {
    "id": "hft_006",
    "asset": "BTC",
    "side": "UP",
    "entry_price": 0.47,
    "entry_time": "2026-05-07T23:53:41.907291+00:00",
    "stake": 1.05,
    "shares": 2.234,
    "signal_score": 0.3248,
    "status": "sold",
    "exit_price": 0.04,
    "exit_time": "2026-05-07T23:54:18.452630+00:00",
    "pnl": -0.96,
    "market_slug": "btc-updown-5m-1778197800",
    "gamma_id": "2178105",
    "event_start": "2026-05-07T23:50:00+00:00",
    "event_end": "2026-05-07T23:55:00+00:00",
    "token_id": "633855605309297636715542794868475958916370762102302172982357570836399279228",
    "exit_reason": "stop_loss"
  },
  {
    "id": "hft_007",
    "asset": "ETH",
    "side": "UP",
    "entry_price": 0.09,
    "entry_time": "2026-05-07T23:53:42.421077+00:00",
    "stake": 1.05,
    "shares": 11.6667,
    "signal_score": 0.3299,
    "status": "sold",
    "exit_price": 0.04,
    "exit_time": "2026-05-07T23:53:58.730595+00:00",
    "pnl": -0.58,
    "market_slug": "eth-updown-5m-1778197800",
    "gamma_id": "2178102",
    "event_start": "2026-05-07T23:50:00+00:00",
    "event_end": "2026-05-07T23:55:00+00:00",
    "token_id": "7778115514674127087480553573384423985770328836156584922400245467595846444582",
    "exit_reason": "stop_loss"
  },
  {
    "id": "hft_008",
    "asset": "BTC",
    "side": "UP",
    "entry_price": 0.65,
    "entry_time": "2026-05-07T23:59:00.665434+00:00",
    "stake": 0.97,
    "shares": 1.4923,
    "signal_score": 0.3771,
    "status": "sold",
    "exit_price": 0.27,
    "exit_time": "2026-05-07T23:59:16.247211+00:00",
    "pnl": -0.57,
    "market_slug": "btc-updown-5m-1778198100",
    "gamma_id": "2178120",
    "event_start": "2026-05-07T23:55:00+00:00",
    "event_end": "2026-05-08T00:00:00+00:00",
    "token_id": "29147140041196728298690855493041613366994214867105721634823959162494430112817",
    "exit_reason": "stop_loss"
  }
]