[
  {
    "id": "hft_001",
    "asset": "ETH",
    "side": "UP",
    "entry_price": 0.5,
    "entry_time": "2026-05-07T22:16:54.310172+00:00",
    "stake": 1.0,
    "shares": 2.0,
    "signal_score": 0.4379,
    "status": "won",
    "exit_price": 1.0,
    "exit_time": "2026-05-07T22:25:36.656425+00:00",
    "pnl": 1.0,
    "market_slug": "eth-updown-5m-1778192100",
    "gamma_id": "2177648",
    "event_start": "2026-05-07T22:15:00+00:00",
    "event_end": "2026-05-07T22:20:00+00:00",
    "token_id": "101478071361273931584880106486496631828465715689735947186430738770987246790818"
  }
]